{
  "project_info": {
    "project_number": "440640646783",
    "firebase_url": "https://chat-cs6250-2017.firebaseio.com",
    "project_id": "chat-cs6250-2017",
    "storage_bucket": "chat-cs6250-2017.appspot.com"
  },
  "client": [
    {
      "client_info": {
        "mobilesdk_app_id": "1:440640646783:android:55b96633bb34c794",
        "android_client_info": {
          "package_name": "com.braunster.androidchatsdk.firebaseplugin"
        }
      },
      "oauth_client": [
        {
          "client_id": "440640646783-dvbdbhu61akktdh1ij59p9iu0ihgodl5.apps.googleusercontent.com",
          "client_type": 3
        }
      ],
      "api_key": [
        {
          "current_key": "AIzaSyD1pNxJi5ls5bdyL-pKkRtJXRdXKa8-Xzs"
        }
      ],
      "services": {
        "analytics_service": {
          "status": 1
        },
        "appinvite_service": {
          "status": 1,
          "other_platform_oauth_client": []
        },
        "ads_service": {
          "status": 2
        }
      }
    },
    {
      "client_info": {
        "mobilesdk_app_id": "1:440640646783:android:2f90496f1e628df1",
        "android_client_info": {
          "package_name": "com.braunster.androidchatsdk.app"
        }
      },
      "oauth_client": [
        {
          "client_id": "440640646783-dvbdbhu61akktdh1ij59p9iu0ihgodl5.apps.googleusercontent.com",
          "client_type": 3
        }
      ],
      "api_key": [
        {
          "current_key": "AIzaSyD1pNxJi5ls5bdyL-pKkRtJXRdXKa8-Xzs"
        }
      ],
      "services": {
        "analytics_service": {
          "status": 1
        },
        "appinvite_service": {
          "status": 1,
          "other_platform_oauth_client": []
        },
        "ads_service": {
          "status": 2
        }
      }
    }
  ],
  "configuration_version": "1"
}